Topsis_Akshat/__init__.py
Topsis_Akshat/topsis.py
Topsis_Akshat_102017147-1.0.4.dist-info/LICENSE.txt
Topsis_Akshat_102017147-1.0.4.dist-info/METADATA
Topsis_Akshat_102017147-1.0.4.dist-info/WHEEL
Topsis_Akshat_102017147-1.0.4.dist-info/entry_points.txt
Topsis_Akshat_102017147-1.0.4.dist-info/top_level.txt
Topsis_Akshat_102017147-1.0.4.dist-info/RECORD
