Metadata-Version: 2.1
Name: Topsis-Akshat-102017147
Version: 1.0.4
Summary: Calculates Topsis Score and Rank them accordingly
Home-page: https://github.com/AkshatGirdhar02/Topsis_Akshat
Author: Akshat Girdhar
Author-email: akshatgirdhar02@gmail.com
License: MIT
Classifier: Programming Language :: Python :: 3
Classifier: License :: OSI Approved :: MIT License
Classifier: Operating System :: OS Independent
License-File: LICENSE.txt
Requires-Dist: pandas
